ansiqa/__init__.py
ansiqa/load.py
ansiqa-0.3.0.dist-info/LICENSE
ansiqa-0.3.0.dist-info/METADATA
ansiqa-0.3.0.dist-info/WHEEL
ansiqa-0.3.0.dist-info/entry_points.txt
ansiqa-0.3.0.dist-info/top_level.txt
ansiqa-0.3.0.dist-info/RECORD
