Metadata-Version: 2.1
Name: ansiqa
Version: 0.3.0
Summary: Anisible Role Quality Assurance
Home-page: https://github.com/kulinacs/ansiqa
Author: kulinacs
Author-email: nicklaus@kulinacs.com
License: ISC
Keywords: ansible automation documentation
Platform: UNKNOWN
Classifier: Development Status :: 3 - Alpha
Classifier: Intended Audience :: System Administrators
Classifier: Topic :: System :: Systems Administration
Classifier: License :: OSI Approved :: ISC License (ISCL)
Classifier: Programming Language :: Python :: 3.5
Requires-Dist: ruamel.yaml (<0.15)
Requires-Dist: argparse
Requires-Dist: tabulate
Requires-Dist: termcolor
Requires-Dist: jinja2
Requires-Dist: pygraphviz
